ipyreact/__init__.py
ipyreact/_frontend.py
ipyreact/_version.py
ipyreact/basic.tsx
ipyreact/cellmagic.py
ipyreact/importmap.py
ipyreact/module.py
ipyreact/widget.py
ipyreact/labextension/package.json
ipyreact/labextension/static/128.abd397de3ff37346bd22.js
ipyreact/labextension/static/128.abd397de3ff37346bd22.js.LICENSE.txt
ipyreact/labextension/static/131.853aa1b2d96ba4c14b49.js
ipyreact/labextension/static/367.64c21a323760c3e63270.js
ipyreact/labextension/static/480.b92afc3ad10df271e336.js
ipyreact/labextension/static/525.e1841ec9155f0eab0676.js
ipyreact/labextension/static/525.e1841ec9155f0eab0676.js.LICENSE.txt
ipyreact/labextension/static/568.01cd82a618017722af7b.js
ipyreact/labextension/static/730.0711372a30ea4e5b94e3.js
ipyreact/labextension/static/730.0711372a30ea4e5b94e3.js.LICENSE.txt
ipyreact/labextension/static/remoteEntry.928651bedae7be675441.js
ipyreact/labextension/static/style.js
ipyreact/labextension/static/third-party-licenses.json
ipyreact/nbextension/extension.js
ipyreact/nbextension/index.js
ipyreact/nbextension/index.js.LICENSE.txt
ipyreact/nbextension/index.js.map
ipyreact-0.4.2.data/data/share/jupyter/nbextensions/jupyter-react/extension.js
ipyreact-0.4.2.data/data/share/jupyter/nbextensions/jupyter-react/index.js
ipyreact-0.4.2.data/data/share/jupyter/nbextensions/jupyter-react/index.js.LICENSE.txt
ipyreact-0.4.2.data/data/share/jupyter/nbextensions/jupyter-react/index.js.map
ipyreact-0.4.2.data/data/etc/jupyter/nbconfig/notebook.d/ipyreact.json
ipyreact-0.4.2.data/data/share/jupyter/labextensions/@widgetti/jupyter-react/package.json
ipyreact-0.4.2.data/data/share/jupyter/labextensions/@widgetti/jupyter-react/static/128.abd397de3ff37346bd22.js
ipyreact-0.4.2.data/data/share/jupyter/labextensions/@widgetti/jupyter-react/static/128.abd397de3ff37346bd22.js.LICENSE.txt
ipyreact-0.4.2.data/data/share/jupyter/labextensions/@widgetti/jupyter-react/static/131.853aa1b2d96ba4c14b49.js
ipyreact-0.4.2.dist-info/METADATA
ipyreact-0.4.2.dist-info/WHEEL
ipyreact-0.4.2.dist-info/licenses/LICENSE.txt
ipyreact-0.4.2.dist-info/RECORD
