Metadata-Version: 2.3
Name: ipyreact
Version: 0.4.2
Summary: React for ipywidgets that just works
Project-URL: Homepage, https://github.com/widgetti/ipyreact
Author-email: "Maarten A. Breddels" <maartenbreddels@gmail.com>
License: Copyright (c) 2023 Maarten A. Breddels
License-File: LICENSE.txt
Keywords: IPython,Jupyter,Widgets
Classifier: Framework :: Jupyter
Classifier: Intended Audience :: Developers
Classifier: Intended Audience :: Science/Research
Classifier: License :: OSI Approved :: BSD License
Classifier: Programming Language :: Python
Classifier: Programming Language :: Python :: 3
Classifier: Programming Language :: Python :: 3.7
Classifier: Programming Language :: Python :: 3.8
Classifier: Programming Language :: Python :: 3.9
Classifier: Programming Language :: Python :: 3.10
Requires-Python: >=3.7
Requires-Dist: anywidget>=0.2.0
Requires-Dist: ipywidgets>=7.0.0
Provides-Extra: dev
Requires-Dist: pre-commit; extra == 'dev'
Provides-Extra: docs
Requires-Dist: jupyter-sphinx; extra == 'docs'
Requires-Dist: nbsphinx; extra == 'docs'
Requires-Dist: nbsphinx-link; extra == 'docs'
Requires-Dist: pypandoc; extra == 'docs'
Requires-Dist: pytest-check-links; extra == 'docs'
Requires-Dist: recommonmark; extra == 'docs'
Requires-Dist: sphinx-rtd-theme; extra == 'docs'
Requires-Dist: sphinx>=1.5; extra == 'docs'
Provides-Extra: examples
Provides-Extra: ui-test
Requires-Dist: pytest>=6.0; extra == 'ui-test'
Requires-Dist: solara[pytest]; extra == 'ui-test'
Provides-Extra: unit-test
Requires-Dist: pytest>=6.0; extra == 'unit-test'
